Metadata-Version: 2.1
Name: SapFlowSavvy
Version: 0.3
Summary: Toolkit de automatização para SAP Gui
Home-page: https://github.com/Neitan96/SAPFlowSavvy
Author: Nathan Almeida
Author-email: neitan96@outlook.com
License: GPLv3
Keywords: sap sapgui sapscript
License-File: LICENSE
Requires-Dist: win32com
Requires-Dist: pywinauto
Requires-Dist: pymsgbox
